.coveragerc
.gitignore
.pre-commit-config.yaml
AUTHORS.rst
CHANGELOG.rst
LICENSE.txt
README.rst
example.py
requirements.txt
setup.cfg
setup.py
.github/workflows/ci.yaml
docs/Makefile
docs/authors.rst
docs/changelog.rst
docs/conf.py
docs/index.rst
docs/license.rst
docs/_static/.gitignore
src/aio_osservaprezzi/__init__.py
src/aio_osservaprezzi/api.py
src/aio_osservaprezzi/const.py
src/aio_osservaprezzi.egg-info/PKG-INFO
src/aio_osservaprezzi.egg-info/SOURCES.txt
src/aio_osservaprezzi.egg-info/dependency_links.txt
src/aio_osservaprezzi.egg-info/not-zip-safe
src/aio_osservaprezzi.egg-info/requires.txt
src/aio_osservaprezzi.egg-info/top_level.txt
tests/conftest.py
tests/test_skeleton.py