Metadata-Version: 2.1
Name: aio-osservaprezzi
Version: 0.0.2
Summary: Add a short description here!
Home-page: https://pyscaffold.org/
Author: Eliseo Martelli
Author-email: me@eliseomartelli.it
License: mit
Platform: any
Classifier: Development Status :: 4 - Beta
Classifier: Programming Language :: Python
Provides-Extra: testing
